hattrie.so
hat_trie_python-0.6.0.dist-info/RECORD
hat_trie_python-0.6.0.dist-info/METADATA
hat_trie_python-0.6.0.dist-info/top_level.txt
hat_trie_python-0.6.0.dist-info/WHEEL
hat_trie_python-0.6.0.dist-info/LICENSE
