Metadata-Version: 2.1
Name: hat-trie-python
Version: 0.6.0
Summary: Python bindings for Tessil/hat-trie
Home-page: https://github.com/Dobatymo/hat-trie-python
Author: Dobatymo
License: UNKNOWN
Platform: UNKNOWN
Requires-Python: >=2.7
